sphinx_markdown_builder/__init__.py
sphinx_markdown_builder/builder.py
sphinx_markdown_builder/contexts.py
sphinx_markdown_builder/escape.py
sphinx_markdown_builder/translator.py
sphinx_markdown_builder/writer.py
sphinx_markdown_builder-0.6.9.dist-info/METADATA
sphinx_markdown_builder-0.6.9.dist-info/WHEEL
sphinx_markdown_builder-0.6.9.dist-info/entry_points.txt
sphinx_markdown_builder-0.6.9.dist-info/top_level.txt
sphinx_markdown_builder-0.6.9.dist-info/RECORD
