Metadata-Version: 2.4
Name: sphinx-markdown-builder
Version: 0.6.9
Summary: A Sphinx extension to add markdown generation support.
Author-email: Liran Funaro <liran.funaro@gmail.com>
License-Expression: MIT
Project-URL: Homepage, https://github.com/liran-funaro/sphinx-markdown-builder
Keywords: sphinx,sphinx-extension,markdown,docs,documentation,builder
Classifier: Framework :: Sphinx :: Extension
Classifier: Programming Language :: Python
Classifier: Programming Language :: Python :: 3
Classifier: Operating System :: OS Independent
Classifier: Topic :: Software Development :: Libraries :: Python Modules
Requires-Python: >=3.7
Requires-Dist: sphinx>=5.1.0
Requires-Dist: tabulate
Requires-Dist: docutils
Provides-Extra: dev
Requires-Dist: sphinx>=9.0.4; extra == "dev"
Requires-Dist: bumpver; extra == "dev"
Requires-Dist: black; extra == "dev"
Requires-Dist: isort; extra == "dev"
Requires-Dist: flake8; extra == "dev"
Requires-Dist: pylint; extra == "dev"
Requires-Dist: pip-tools; extra == "dev"
Requires-Dist: pytest; extra == "dev"
Requires-Dist: pytest-cov; extra == "dev"
Requires-Dist: coveralls; extra == "dev"
Requires-Dist: sphinxcontrib-plantuml; extra == "dev"
Requires-Dist: sphinxcontrib.httpdomain; extra == "dev"
